README.md
nester.py
setup.py
nester0101.egg-info/PKG-INFO
nester0101.egg-info/SOURCES.txt
nester0101.egg-info/dependency_links.txt
nester0101.egg-info/top_level.txt