Metadata-Version: 2.1
Name: nester0101
Version: 1.0.3
Summary: a temp def use by first.
Home-page: 
Author: yunlk
Author-email: 1188846330@qq.com
